gutarik/__init__.py
gutarik/config_loader.py
gutarik/generate_docs.py
gutarik/validate_config.py
gutarik-0.1.0.dist-info/METADATA
gutarik-0.1.0.dist-info/WHEEL
gutarik-0.1.0.dist-info/entry_points.txt
gutarik-0.1.0.dist-info/RECORD
